vm_custom_package/auth/__init__.pyd
vm_custom_package/auth/auth.pyd
vm_custom_package/common/__init__.pyd
vm_custom_package/common/exception.pyd
vm_custom_package/common/request.pyd
vm_custom_package/conf/__init__.pyd
vm_custom_package/conf/utils.pyd
vm_custom_package/logger/__init__.pyd
vm_custom_package/logger/apps.pyd
vm_custom_package/logger/logging.pyd
vm_custom_package/proxy/__init__.pyd
vm_custom_package/proxy/handle_proxy.pyd
vm_custom_package/proxy/site.pyd
vm_custom_package/utils/__init__.pyd
vm_custom_package/utils/characters.pyd
vm_custom_package/utils/dates.pyd
vm_custom_package/utils/error.pyd
vm_custom_package/utils/utils.pyd
vm_custom_package/vm_django/__init__.pyd
vm_custom_package/vm_django/database.pyd
vm_custom_package/vm_django/django_logger.pyd
vm_custom_package/vm_django/middleware.pyd
vm_custom_package/vm_django/model.pyd
vm_custom_package/vm_django/vm_serializers.pyd
vm_custom_package-0.1.5.113.dist-info/LICENCE
vm_custom_package-0.1.5.113.dist-info/METADATA
vm_custom_package-0.1.5.113.dist-info/WHEEL
vm_custom_package-0.1.5.113.dist-info/top_level.txt
vm_custom_package-0.1.5.113.dist-info/RECORD
