Metadata-Version: 2.1
Name: vm_custom_package
Version: 0.1.5.113
Summary: Custom project.
Author: Vahid Moslemi
Project-URL: homepage, https://github.com/
License-File: LICENCE
Requires-Dist: setuptools>=42
Requires-Dist: wheel
Requires-Dist: toml
Requires-Dist: jsonschema
Requires-Dist: python-telegram-bot>=21.2
Requires-Dist: psutil>=5.9.8
Requires-Dist: requests>=2.32.2
Requires-Dist: jdatetime>=5.0.0
Requires-Dist: django>=4.2.13
Requires-Dist: cryptography>=43.0.0
Requires-Dist: loguru>=0.7.2
Requires-Dist: beautifulsoup4>=4.13.4
Requires-Dist: selenium>=4.31.0
Requires-Dist: selenium-wire>=5.1.0
Requires-Dist: typing-extensions; python_version < "3.8"
